flatplan/__init__.py
flatplan/configuration.py
flatplan/flattener.py
flatplan/hooks.py
flatplan/logging.py
flatplan/main.py
flatplan-1.3.0.dist-info/LICENSE
flatplan-1.3.0.dist-info/METADATA
flatplan-1.3.0.dist-info/WHEEL
flatplan-1.3.0.dist-info/entry_points.txt
flatplan-1.3.0.dist-info/top_level.txt
flatplan-1.3.0.dist-info/RECORD
