Metadata-Version: 2.1
Name: flatplan
Version: 1.3.0
Summary: Flatplan is a tool that groups all resources and providers specified in a Terraform plan or state file
Home-page: https://github.com/egonbraun/python-project-template
Author: Egon Braun
Author-email: egon@mundoalem.io
License: UNKNOWN
Project-URL: Bug Reports, https://github.com/egonbraun/flatplan/issues
Project-URL: Source, https://github.com/egonbraun/flatplan
Keywords: terraform,plan,state,tools,cli
Platform: UNKNOWN
Classifier: Development Status :: 3 - Alpha
Classifier: Intended Audience :: Developers
Classifier: Topic :: Software Development :: Build Tools
Classifier: License :: OSI Approved :: GNU General Public License v3 (GPLv3)
Classifier: Programming Language :: Python :: 3
Classifier: Programming Language :: Python :: 3.7
Classifier: Programming Language :: Python :: 3.8
Classifier: Programming Language :: Python :: 3.9
Classifier: Programming Language :: Python :: 3 :: Only
Requires-Python: >=3.7, <4
Requires-Dist: colorama
Requires-Dist: coloredlogs
Requires-Dist: fire
Provides-Extra: dev
Requires-Dist: black ; extra == 'dev'
Requires-Dist: coverage ; extra == 'dev'
Requires-Dist: pytest ; extra == 'dev'
Requires-Dist: sphinx ; extra == 'dev'
Requires-Dist: tox ; extra == 'dev'
Requires-Dist: twine ; extra == 'dev'
